configupdater/__init__.py
configupdater/block.py
configupdater/builder.py
configupdater/configupdater.py
configupdater/container.py
configupdater/document.py
configupdater/option.py
configupdater/parser.py
configupdater/py.typed
configupdater/section.py
ConfigUpdater-3.1.1.dist-info/LICENSE.txt
ConfigUpdater-3.1.1.dist-info/METADATA
ConfigUpdater-3.1.1.dist-info/WHEEL
ConfigUpdater-3.1.1.dist-info/top_level.txt
ConfigUpdater-3.1.1.dist-info/RECORD
