Metadata-Version: 2.1
Name: ConfigUpdater
Version: 3.1.1
Summary: Parser like ConfigParser but for updating configuration files
Home-page: https://github.com/pyscaffold/configupdater
Author: Florian Wilhelm
Author-email: florian.wilhelm@gmail.com
License: MIT
Project-URL: Documentation, https://configupdater.readthedocs.io/
Project-URL: Source, https://github.com/pyscaffold/configupdater/
Project-URL: Tracker, https://github.com/pyscaffold/configupdater/issues
Project-URL: Changelog, https://configupdater.readthedocs.io/en/latest/changelog.html
Project-URL: Download, https://pypi.org/project/configupdater/#files
Project-URL: Conda-Forge, https://anaconda.org/conda-forge/configupdater
Platform: any
Classifier: Development Status :: 5 - Production/Stable
Classifier: Programming Language :: Python :: 3
Classifier: Programming Language :: Python :: 3 :: Only
Classifier: Programming Language :: Python :: 3.6
Classifier: Programming Language :: Python :: 3.7
Classifier: Programming Language :: Python :: 3.8
Classifier: Topic :: Software Development :: Libraries :: Python Modules
Classifier: Operating System :: OS Independent
Classifier: License :: OSI Approved :: MIT License
Classifier: Intended Audience :: Developers
Classifier: Operating System :: POSIX :: Linux
Classifier: Operating System :: Unix
Classifier: Operating System :: MacOS
Classifier: Operating System :: Microsoft :: Windows
Requires-Python: >=3.6
Provides-Extra: testing
License-File: LICENSE.txt
